eptransition/__init__.py
eptransition/exceptions.py
eptransition/manager.py
eptransition/settings.py
eptransition/transition.py
eptransition/rules/__init__.py
eptransition/rules/base_rule.py
eptransition/rules/version_rule.py
eptransition/rules/rules85to86/__init__.py
eptransition/rules/rules85to86/air_terminal_vav_reheat.py
eptransition/rules/rules85to86/airterminal_singleduct_inletsidemixer.py
eptransition/rules/rules85to86/airterminal_singleduct_supplysidemixer.py
eptransition/rules/rules85to86/branch.py
eptransition/rules/rules85to86/chillerheater.py
eptransition/rules/rules85to86/coilheatinggas.py
eptransition/rules/rules85to86/daylighting.py
eptransition/rules/rules85to86/empd.py
eptransition/rules/rules85to86/ems_actuator.py
eptransition/rules/rules85to86/exteriorfuelequipment.py
eptransition/rules/rules85to86/otherequipment.py
eptransition/rules/rules85to86/output_variables.py
eptransition/rules/rules85to86/setpoint_managers.py
eptransition/rules/rules85to86/utilities.py
eptransition/rules/rules85to86/zonehvac_airdistributionunit.py
eptransition/rules/rules86to87/__init__.py
eptransition/rules/templates/__init__.py
eptransition/rules/templates/remove_single_field.py
eptransition/versions/__init__.py
eptransition/versions/versions.py
eptransition/versions/8.5/Energy+.idd
eptransition/versions/8.6/Energy+.idd
eptransition/versions/8.7/Energy+.idd
eptransition-0.952.dist-info/DESCRIPTION.rst
eptransition-0.952.dist-info/METADATA
eptransition-0.952.dist-info/RECORD
eptransition-0.952.dist-info/WHEEL
eptransition-0.952.dist-info/entry_points.txt
eptransition-0.952.dist-info/metadata.json
eptransition-0.952.dist-info/top_level.txt
